pyipums/__init__.py
pyipums/clean_data.py
pyipums/parse_xml.py
pyipums-0.0.4.dist-info/LICENSE
pyipums-0.0.4.dist-info/METADATA
pyipums-0.0.4.dist-info/WHEEL
pyipums-0.0.4.dist-info/RECORD
